{
  "spacing": {
    "dimension-00": "0",
    "dimension-25": "2",
    "dimension-50": "4",
    "dimension-75": "6",
    "dimension-100": "8",
    "dimension-125": "10",
    "dimension-150": "12",
    "dimension-200": "16",
    "dimension-225": "18",
    "dimension-250": "20",
    "dimension-300": "24",
    "dimension-350": "28",
    "dimension-375": "30",
    "dimension-400": "32",
    "dimension-500": "40",
    "dimension-600": "48",
    "dimension-700": "56",
    "dimension-750": "60",
    "dimension-800": "64",
    "dimension-900": "72",
    "dimension-950": "76",
    "dimension-1000": "80",
    "dimension-1100": "88",
    "dimension-1150": "92",
    "dimension-1200": "100",
    "dimension-1300": "108",
    "dimension-1400": "116",
    "dimension-1500": "124",
    "dimension-1600": "132",
    "dimension-1700": "140",
    "dimension-1800": "148",
    "dimension-1900": "156",
    "dimension-2000": "164",
    "dimension-2100": "172",
    "dimension-2200": "180",
    "dimension-2300": "188",
    "dimension-2400": "196",
    "dimension-2500": "204",
    "dimension-2600": "212",
    "dimension-2700": "220",
    "dimension-2800": "228",
    "dimension-2900": "236",
    "dimension-3000": "244"
  },
  "borderRadius": {
    "corner-radius-25": "2",
    "corner-radius-50": "4",
    "corner-radius-75": "6",
    "corner-radius-100": "8",
    "corner-radius-200": "16",
    "corner-radius-250": "20",
    "corner-radius-full": "9999"
  },
  "transitionDuration": {
    "duration-150": "150ms",
    "duration-250": "250ms",
    "duration-350": "350ms",
    "duration-400": "400ms",
    "duration-500": "500ms",
    "duration-800": "800ms"
  },
  "screens": {
    "max-w-700": "700",
    "max-w-1280": "1280",
    "max-w-2560": "2560"
  }
}